{"id": "ANT498H5F20189", "code": "ANT498H5F", "name": "Advanced Independent Study", "description": "This independent study course is designed to offer students advanced supervised reading, research and planning for a publishable report on an anthropological topic not covered in other courses, or covered only briefly. Students who wish to pursue this option with a specific faculty member should approach the faculty member early - before the start of the academic term - to negotiate the research and study program. The faculty member should then discuss the proposal with the Chair or designate, prior to further planning. A syllabus must be submitted to the Chair or designate through the online CISS system for approval of the course. Registration by the student online is required.", "division": "University of Toronto Mississauga", "department": "Anthropology", "prerequisites": "Permission of Instructor and Permission of Department", "exclusions": "", "level": 400, "campus": "UTM", "term": "2018 Fall", "breadths": [], "meeting_sections": [{"code": "L0101", "instructors": ["D Samson"], "times": [], "size": 1, "enrolment": 0}]}