{"id": "BCH473Y1Y20189", "code": "BCH473Y1Y", "name": "Advanced Research Project in Biochemistry", "description": "This course provides opportunities to pursue an original individual research project in a particular area of biochemistry, under the direct supervision of a Biochemistry Department faculty member. A cGPA of 3.3 is required for students in Major programs and a cGPA of 3.0 is required for students in Specialist programs. Not eligible for CR/NCR option.", "division": "Faculty of Arts and Science", "department": "Biochemistry", "prerequisites": "Specialist: BCH340H1; BCH377H1; BCH378H1; MGY311Y1; and permission of Department. Major: BCH370H1; BCH311H1; and permission of Department.", "exclusions": "", "level": 400, "campus": "UTSG", "term": "2018 Fall", "breadths": [4], "meeting_sections": [{"code": "L0101", "instructors": ["C Smibert"], "times": [], "size": 20, "enrolment": 0}]}