{"id": "CIV550H1F20189", "code": "CIV550H1F", "name": "Water Resources Engineering", "description": "Global and national water problems, law and legislation. Hydraulic structures. Reservoir analysis. Urban drainage and runoff control: meteorologic data analysis, deterministic and stochastic modelling techniques. Flood control: structural and nonstructural alternatives. Power generation: hydro and thermal power generation. Low flow augmentation. Economics and decision making.", "division": "Faculty of Applied Science & Engineering", "department": "Civil and Mineral Engineering", "prerequisites": "CIV250H1, CIV340H1 or equivalent", "exclusions": "", "level": 500, "campus": "UTSG", "term": "2018 Fall", "breadths": [], "meeting_sections": [{"code": "L0101", "instructors": ["J Drake"], "times": [{"day": "MONDAY", "start": 39600, "end": 43200, "duration": 3600, "location": "MY 330"}, {"day": "THURSDAY", "start": 39600, "end": 43200, "duration": 3600, "location": "MY 330"}, {"day": "WEDNESDAY", "start": 39600, "end": 43200, "duration": 3600, "location": "MY 330"}], "size": 50, "enrolment": 0}, {"code": "T0101", "instructors": [], "times": [{"day": "MONDAY", "start": 43200, "end": 50400, "duration": 7200, "location": "MY 370"}], "size": 50, "enrolment": 0}]}