{"id": "CIV515H1F20189", "code": "CIV515H1F", "name": "Introduction to Structural Dynamics", "description": "The concept of dynamic equilibrium and corresponding equation of motion will be introduced.\u00a0 The theoretical solution of a songle degree of freedom system will be derived and the effects of verious types of loads, such as impulse load, sinusoidal load, or random vibration on the structural response will be discussed.\u00a0 To solve dynamic problems of multi-degree of freedom (MDOF) systems, concepts of mass, stiffness, and damping matrix will be introduced, which will be followed by eigen value analysis and modal analysis.\u00a0 The concepts of Fourier Transformation will be introduced, which will be used to interpret dynamic responses of structures or dynamic nature of applied loads.\u00a0 Dynamic experiments of elastic systems will be demonstrated using an educational shaking table.", "division": "Faculty of Applied Science & Engineering", "department": "Civil and Mineral Engineering", "prerequisites": "CIV312H1 and CIV313H1 or equivalent", "exclusions": "", "level": 500, "campus": "UTSG", "term": "2018 Fall", "breadths": [], "meeting_sections": [{"code": "L0101", "instructors": ["O Kwon"], "times": [{"day": "THURSDAY", "start": 54000, "end": 61200, "duration": 7200, "location": "MY 440"}, {"day": "FRIDAY", "start": 57600, "end": 61200, "duration": 3600, "location": "BA 3116"}], "size": 35, "enrolment": 0}, {"code": "T0101", "instructors": [], "times": [{"day": "FRIDAY", "start": 61200, "end": 64800, "duration": 3600, "location": "BA 3116"}], "size": 35, "enrolment": 0}]}