{"id": "DRM403Y1Y20189", "code": "DRM403Y1Y", "name": "Advanced Performance: Mainstage", "description": "This course, taught each year by a different visiting professional theatre director, offers upper-level theatre and performance studies students the opportunity to explore acting in a full-length production. Plays are selected to challenge students in a variety of diverse ways, exposing them to a full spectrum of theatre and performance genres and possibilities. The Application Deadline is March 10th.", "division": "Faculty of Arts and Science", "department": "Centre for Drama, Theatre and Performance Studies", "prerequisites": "Specialist or Major in Drama with a minimum CGPA of 2.7; DRM220Y1/DRM230Y1; DRM300Y1, 1 FCE from DRM375H1/DRM376H1/ DRM377H1/DRM378H1; An audition in April.", "exclusions": "DRS425H5 AND DRS426H5", "level": 400, "campus": "UTSG", "term": "2018 Fall", "breadths": [1], "meeting_sections": [{"code": "L0101", "instructors": ["K Gass M Ross"], "times": [{"day": "TUESDAY", "start": 36000, "end": 46800, "duration": 10800, "location": "UP 201"}, {"day": "THURSDAY", "start": 36000, "end": 46800, "duration": 10800, "location": "UP 201"}], "size": 15, "enrolment": 0}, {"code": "T0101", "instructors": [], "times": [{"day": "FRIDAY", "start": 36000, "end": 46800, "duration": 10800, "location": "UP 201"}], "size": 15, "enrolment": 0}]}