{"id": "EAS378H1S20191", "code": "EAS378H1S", "name": "Edo, Osaka, and Kyoto: Urban Life in Early Modern Japan", "description": "An exploration of most important cities of Tokugawa Japan, which were among the largest of the early modern world, and home to vibrant urban culture and economic activity. The texts include buildings, maps, paintings, prints, film and novels.", "division": "Faculty of Arts and Science", "department": "East Asian Studies", "prerequisites": "EAS105H1 and EAS209H1", "exclusions": "", "level": 300, "campus": "UTSG", "term": "2019 Winter", "breadths": [3], "meeting_sections": [{"code": "L5101", "instructors": ["T Keirstead"], "times": [{"day": "WEDNESDAY", "start": 61200, "end": 68400, "duration": 7200, "location": "SS 1084"}], "size": 45, "enrolment": 0}]}