{"id": "ECO461H1S20191", "code": "ECO461H1S", "name": "The Economics of Financial Risk Management", "description": "This course is intended primarily for students in the Financial Economics specialist program and is not open to students in the BCom program. The role of risk management in both private and public sectors, a discussion of why firms and government should hedge financial risks; individual and social gains of financial risk management; identification and quantification of financial risks (including Value-at-Risk measures); how derivative securities can be used for financial risk management.", "division": "Faculty of Arts and Science", "department": "Economics", "prerequisites": "ECO358H1(70%)", "exclusions": "ACT349H1, RSM332H1, RSM333H1, RSM435H1, ECO460H5, ECO461H5", "level": 400, "campus": "UTSG", "term": "2019 Winter", "breadths": [3], "meeting_sections": [{"code": "L0101", "instructors": ["A Mazaheri"], "times": [{"day": "TUESDAY", "start": 32400, "end": 43200, "duration": 10800, "location": "WI 1017"}], "size": 80, "enrolment": 0}]}