{"id": "ENV323H1S20191", "code": "ENV323H1S", "name": "Ontario Environmental Policy", "description": "Introduces students to public policy and institutional foundations of public policy in Canada, with an emphasis on environmental policy in Ontario. Provides an insiders perspective on how environmental policy has been developed in Ontario.", "division": "Faculty of Arts and Science", "department": "School of Environment", "prerequisites": "(ENV221H1, ENV222H1) and completion of at least 8 FCE of courses; or permission of the Undergraduate Associate Director.", "exclusions": "ENV423H1", "level": 300, "campus": "UTSG", "term": "2019 Winter", "breadths": [3], "meeting_sections": [{"code": "L0101", "instructors": ["R Houldin"], "times": [{"day": "MONDAY", "start": 36000, "end": 43200, "duration": 7200, "location": "AB 107"}], "size": 60, "enrolment": 0}]}