{"id": "ENV432H1F20189", "code": "ENV432H1F", "name": "Urban Ecology", "description": "The ecology of urban areas through consideration of the biological and physical environments, in particular how the human-constructed environment alters pre-existing biophysical conditions and interactions. Encompasses a comparative perspective to study the development of these emerging ecosystems of increasing importance given global urbanization. One or two Saturday field trips (a fee of approximately $15 may be charged for field trip transportation.)", "division": "Faculty of Arts and Science", "department": "Ecology and Evolutionary Biology", "prerequisites": "At least one of EEB319H1/EEB321H1/EEB365H1/ENV334H1", "exclusions": "", "level": 400, "campus": "UTSG", "term": "2018 Fall", "breadths": [4], "meeting_sections": [{"code": "L0101", "instructors": ["K Ing D Jackson"], "times": [{"day": "WEDNESDAY", "start": 32400, "end": 43200, "duration": 10800, "location": "BA 2165"}], "size": 36, "enrolment": 0}]}