{"id": "EST200H1F20189", "code": "EST200H1F", "name": "Intermediate Estonian Language and Culture I", "description": "This course develops the student's language skills via an exploration of Estonian culture - including its music, literature, film and media. Each of these areas will be examined through readings, writing about one\u2019s impressions, and speaking about them to others in the class. The course consists of a combination of both classroom and web-based learning. The course is open to students with some fluency in Estonian.", "division": "Faculty of Arts and Science", "department": "Slavic Languages and Literatures", "prerequisites": "(EST100H1, EST101H1) / Permission of instructor", "exclusions": "EST200Y1", "level": 200, "campus": "UTSG", "term": "2018 Fall", "breadths": [1], "meeting_sections": []}