{"id": "FAH341H1S20195S", "code": "FAH341H1S2", "name": "Venetian Renaissance Art and Architecture", "description": "Form and meaning, theory and practice of painting and architecture in Venice, ca. 1450-ca. 1600. Social, political and cultural contexts of making and viewing art, including works by Giorgione, Titian, Veronese, Tintoretto and Palladio.", "division": "Faculty of Arts and Science", "department": "Art", "prerequisites": "FAH230H1/FAH231H1/274H1/279H1", "exclusions": "", "level": 300, "campus": "UTSG", "term": "2019 Summer S", "breadths": [1], "meeting_sections": [{"code": "L0101", "instructors": [], "times": [{"day": "TUESDAY", "start": 50400, "end": 57600, "duration": 7200, "location": "SS 2111"}, {"day": "THURSDAY", "start": 50400, "end": 57600, "duration": 7200, "location": "SS 2111"}], "size": 30, "enrolment": 19}]}