{"id": "FCS292H1F20195F", "code": "FCS292H1F2", "name": "Special Topics in French Cultural Studies I", "description": "The relation of French popular culture to society. For more information, see http://www.french.utoronto.ca/undergraduate/courses/french_cultural_studies", "division": "Faculty of Arts and Science", "department": "French", "prerequisites": "None", "exclusions": "", "level": 200, "campus": "UTSG", "term": "2019 Summer F", "breadths": [1], "meeting_sections": [{"code": "L9901", "instructors": ["M Visoi"], "times": [], "size": 60, "enrolment": 60}]}