{"id": "GGR210H5F20189", "code": "GGR210H5F", "name": "Social Geographies", "description": "Social geography is concerned with the ways in which social relations, identities and inequalities are produced across space. This course examines social geography in the North American context with a specific focus on identity/difference and inequalities in cities. We will explore cities as sites of both cosmopolitan inclusion and exclusion. [24L]", "division": "University of Toronto Mississauga", "department": "Geography", "prerequisites": "4.0 credits including GGR111H5", "exclusions": "", "level": 200, "campus": "UTM", "term": "2018 Fall", "breadths": [], "meeting_sections": [{"code": "L0101", "instructors": ["N Laliberte"], "times": [{"day": "WEDNESDAY", "start": 57600, "end": 64800, "duration": 7200, "location": "IB 235"}], "size": 100, "enrolment": 0}]}