{"id": "GGR203H1F20189", "code": "GGR203H1F", "name": "Introduction to Climatology", "description": "Introduction to the large scale processes responsible for determining global and regional climate and atmospheric circulation patterns, as well as the small scale processes responsible for determining the microclimates of specific environments.", "division": "Faculty of Arts and Science", "department": "Geography and Planning", "prerequisites": "Physics SPH3U", "exclusions": "", "level": 200, "campus": "UTSG", "term": "2018 Fall", "breadths": [5], "meeting_sections": [{"code": "L0101", "instructors": ["L Harvey"], "times": [{"day": "MONDAY", "start": 43200, "end": 46800, "duration": 3600, "location": "ES B142"}, {"day": "WEDNESDAY", "start": 43200, "end": 50400, "duration": 7200, "location": "ES B142"}], "size": 60, "enrolment": 0}]}