{"id": "HIS390H5S20191", "code": "HIS390H5S", "name": "Revolutions and Nations in Latin America", "description": "Examines social revolutions in Guatemala, Bolivia, Cuba and Nicaragua. It emphasizes the historical linkages between these revolutions and national identity, and stresses the roles of gender, race and the United States in revolutionary processes. This course considers as well the counterrevolutionary politics of the 1970s and 1980s in Central America and the Southern cone. [24L]", "division": "University of Toronto Mississauga", "department": "Historical Studies", "prerequisites": "", "exclusions": "", "level": 300, "campus": "UTM", "term": "2019 Winter", "breadths": [], "meeting_sections": [{"code": "L0101", "instructors": ["E Toffoli"], "times": [{"day": "WEDNESDAY", "start": 46800, "end": 54000, "duration": 7200, "location": "IB 240"}], "size": 45, "enrolment": 0}]}