{"id": "HIS395H1F20189", "code": "HIS395H1F", "name": "Independent Studies", "description": "This course provides an opportunity for exceptional third-year students to undertake an independent research project on a topic for which there is not a suitable course offering. Students must find an appropriate supervisor from the Department, submit a proposal, and receive approval for the project. Students must be enrolled in either a History Specialist or Major program; have taken at least 3.0 FCE in HIS with a B+ average; and have approval of an instructor willing to supervise the project. Not eligible for CR/NCR option.", "division": "Faculty of Arts and Science", "department": "History", "prerequisites": "Third-year standing; 77% average in 3.0 HIS FCEs.", "exclusions": "", "level": 300, "campus": "UTSG", "term": "2018 Fall", "breadths": [], "meeting_sections": [{"code": "L0101", "instructors": [], "times": [], "size": 9999, "enrolment": 0}]}