{"id": "HMB321H1S20191", "code": "HMB321H1S", "name": "Topics in Genetics", "description": "The overall theme of this course is human genetics in disease. Topics include the molecular basis of human disease, using model organisms to identify disease-related genes, and genetic counseling. Expert guest lectures from clinical and basic sciences as well as small group work in tutorials build in-depth understanding.", "division": "Faculty of Arts and Science", "department": "Human Biology Program", "prerequisites": "9 FCE completed, HMB265H1/ BIO260H1", "exclusions": "", "level": 300, "campus": "UTSG", "term": "2019 Winter", "breadths": [4], "meeting_sections": [{"code": "T0101", "instructors": [], "times": [{"day": "WEDNESDAY", "start": 54000, "end": 57600, "duration": 3600, "location": "WE 51"}], "size": 26, "enrolment": 0}, {"code": "T0102", "instructors": [], "times": [{"day": "WEDNESDAY", "start": 54000, "end": 57600, "duration": 3600, "location": "WE 54"}], "size": 25, "enrolment": 0}, {"code": "T0201", "instructors": [], "times": [{"day": "WEDNESDAY", "start": 57600, "end": 61200, "duration": 3600, "location": "WE 51"}], "size": 25, "enrolment": 0}, {"code": "T0202", "instructors": [], "times": [{"day": "WEDNESDAY", "start": 57600, "end": 61200, "duration": 3600, "location": "WE 54"}], "size": 25, "enrolment": 0}, {"code": "L0101", "instructors": ["M Papaconstantinou"], "times": [{"day": "WEDNESDAY", "start": 46800, "end": 50400, "duration": 3600, "location": "WI 1017"}, {"day": "FRIDAY", "start": 46800, "end": 50400, "duration": 3600, "location": "WI 1017"}], "size": 100, "enrolment": 0}]}