{"id": "HMB437H1S20191", "code": "HMB437H1S", "name": "The Biology of the Human Metallome", "description": "This course will discuss how heavy metals are integral to organ function through various biological pathways, the importance of metal regulation and control and its relationship with gene transcription. An introduction of metallo-therapeutics will also be featured, ranging from neurodegenerative therapies to cancer treatment.", "division": "Faculty of Arts and Science", "department": "Human Biology Program", "prerequisites": "14 FCE complete, HMB265H1/BIO260H1, BIO230H1/ BIO255H1, BCH210H1", "exclusions": "", "level": 400, "campus": "UTSG", "term": "2019 Winter", "breadths": [4], "meeting_sections": [{"code": "L0101", "instructors": ["A Dias"], "times": [{"day": "WEDNESDAY", "start": 39600, "end": 46800, "duration": 7200, "location": "WI 524"}], "size": 50, "enrolment": 0}]}