{"id": "HPS498H1S20191", "code": "HPS498H1S", "name": "Individual Studies", "description": "A reading and research project in some aspect of the development of scientific theory or practice, supervised by a faculty member.", "division": "Faculty of Arts and Science", "department": "Inst. for the History & Philosophy of Science & Technology", "prerequisites": "Two HPS courses", "exclusions": "", "level": 400, "campus": "UTSG", "term": "2019 Winter", "breadths": [], "meeting_sections": [{"code": "L0101", "instructors": [], "times": [], "size": 9999, "enrolment": 0}]}