{"id": "INI300H1F20195F", "code": "INI300H1F2", "name": "Strategic Writing in Business and the Professions: Theory and Practice", "description": "Aims to teach students to recognize the rhetoric of the professional workplace and to communicate strategically and ethically using written and oral discourse appropriate to business, government, and not-for-profit organizations. Case study analysis using ethical reasoning models is a central component of the course.", "division": "Faculty of Arts and Science", "department": "Innis College", "prerequisites": "Completion of 4.0 full-course equivalents.", "exclusions": "INI300Y1; INI302H1", "level": 300, "campus": "UTSG", "term": "2019 Summer F", "breadths": [1], "meeting_sections": [{"code": "L0101", "instructors": [], "times": [{"day": "TUESDAY", "start": 36000, "end": 46800, "duration": 10800, "location": "RW 143"}, {"day": "THURSDAY", "start": 36000, "end": 46800, "duration": 10800, "location": "RW 143"}], "size": 55, "enrolment": 30}]}