{"id": "JLP471H1S20191", "code": "JLP471H1S", "name": "Advanced Psycholinguistics", "description": "Seminar in advanced topics in psycholinguistics. Content varies from year to year. (Sponsored by the Departments of Linguistics and Psychology, but administered solely by the Dept. of Linguisitics).", "division": "Faculty of Arts and Science", "department": "Linguistics", "prerequisites": "JLP374H1", "exclusions": "", "level": 400, "campus": "UTSG", "term": "2019 Winter", "breadths": [2], "meeting_sections": [{"code": "L0101", "instructors": ["D Heller"], "times": [{"day": "THURSDAY", "start": 36000, "end": 43200, "duration": 7200, "location": "ES 4000"}], "size": 22, "enrolment": 0}]}