{"id": "LMP365H1S20191", "code": "LMP365H1S", "name": "Neoplasia", "description": "A general introduction to the cellular and molecular aspects of cancer and its etiology. The laboratory component presents the range of benign and malignant tumor types at the gross and histological levels. Pathophysiology of cancer, invasion and metastases, role of the immune system.", "division": "Faculty of Arts and Science", "department": "Laboratory Medicine and Pathobiology", "prerequisites": "", "exclusions": "", "level": 300, "campus": "UTSG", "term": "2019 Winter", "breadths": [4], "meeting_sections": [{"code": "L0101", "instructors": ["L D'Cunha H Elsholtz"], "times": [{"day": "THURSDAY", "start": 46800, "end": 54000, "duration": 7200, "location": "MS 4171"}], "size": 35, "enrolment": 0}]}