{"id": "MGY378H1S20191", "code": "MGY378H1S", "name": "Microbiology II: Viruses", "description": "Detailed study of viruses in terms of structure, classification, replication and interaction with the host. Basis for advanced study in virology. Requires some familiarity with molecular and cellular biology. A concurrent course in immunology (IMM340H1, IMM350H1) or (IMM341H1, IMM351H1) is recommended.", "division": "Faculty of Arts and Science", "department": "Molecular Genetics", "prerequisites": "BCH210H1/BCH242Y1; BIO120H1, BIO230H1/BIO255H1; BIO260H1/HMB265H1", "exclusions": "BIO351Y1, CSB351Y1", "level": 300, "campus": "UTSG", "term": "2019 Winter", "breadths": [4], "meeting_sections": [{"code": "L0101", "instructors": ["M Brown L Frappier S Mubareka"], "times": [{"day": "MONDAY", "start": 43200, "end": 46800, "duration": 3600, "location": "PB B150"}, {"day": "WEDNESDAY", "start": 43200, "end": 46800, "duration": 3600, "location": "PB B150"}, {"day": "FRIDAY", "start": 43200, "end": 46800, "duration": 3600, "location": "PB B150"}], "size": 196, "enrolment": 0}]}