{"id": "MIE242H1F20189", "code": "MIE242H1F", "name": "Psychology For Engineers", "description": "Introduction to neuroanatomy and processes that are core to perception, cognition, language, decision making, and action. Use of experiments to test hypotheses concerning brain activities and computations. Conducting and reporting experimental research, use of elementary statistics, and satisfaction of research ethics requirements.", "division": "Faculty of Applied Science & Engineering", "department": "Mechanical & Industrial Engineering", "prerequisites": "", "exclusions": "", "level": 200, "campus": "UTSG", "term": "2018 Fall", "breadths": [], "meeting_sections": [{"code": "L0101", "instructors": ["H Vasquez"], "times": [{"day": "WEDNESDAY", "start": 50400, "end": 54000, "duration": 3600, "location": "MS 2170"}, {"day": "MONDAY", "start": 50400, "end": 54000, "duration": 3600, "location": "MS 2170"}, {"day": "FRIDAY", "start": 50400, "end": 54000, "duration": 3600, "location": "MS 2170"}], "size": 124, "enrolment": 0}, {"code": "P0101", "instructors": [], "times": [{"day": "THURSDAY", "start": 43200, "end": 54000, "duration": 10800, "location": "MY 330"}, {"day": "THURSDAY", "start": 43200, "end": 54000, "duration": 10800, "location": "GB 150"}], "size": 63, "enrolment": 0}, {"code": "P0102", "instructors": [], "times": [{"day": "WEDNESDAY", "start": 32400, "end": 43200, "duration": 10800, "location": "MY 380"}, {"day": "WEDNESDAY", "start": 32400, "end": 43200, "duration": 10800, "location": "GB 144"}], "size": 63, "enrolment": 0}]}