{"id": "MIE442H1F20189", "code": "MIE442H1F", "name": "Machine Design", "description": "Introduction to the fundamental elements of mechanical design including the selection of engineering materials, load determination and failure analysis under static, impact, vibration and cyclic loads. Surface failure and fatigue under contact loads, lubrication and wear.\u00a0 Consideration is given to the characteristics and selection of machine elements such as bearings, shafts, power screws and couplings.", "division": "Faculty of Applied Science & Engineering", "department": "Mechanical & Industrial Engineering", "prerequisites": "MIE320H1", "exclusions": "", "level": 400, "campus": "UTSG", "term": "2018 Fall", "breadths": [], "meeting_sections": [{"code": "L0101", "instructors": ["J Spelt"], "times": [{"day": "TUESDAY", "start": 54000, "end": 61200, "duration": 7200, "location": "GB 120"}, {"day": "FRIDAY", "start": 54000, "end": 57600, "duration": 3600, "location": "GB 120"}], "size": 100, "enrolment": 0}, {"code": "P0101", "instructors": [], "times": [{"day": "WEDNESDAY", "start": 64800, "end": 68400, "duration": 3600, "location": "BA 2179"}], "size": 100, "enrolment": 0}, {"code": "T0101", "instructors": [], "times": [{"day": "TUESDAY", "start": 32400, "end": 37800, "duration": 5400, "location": "BA 2145"}], "size": 50, "enrolment": 0}, {"code": "T0102", "instructors": [], "times": [{"day": "TUESDAY", "start": 37800, "end": 43200, "duration": 5400, "location": "BA 2145"}], "size": 50, "enrolment": 0}]}