{"id": "NEW351Y1Y20189", "code": "NEW351Y1Y", "name": "African Systems of Thought", "description": "The exploration of a range of African cosmologies, epistemologies, and theologies, as well as specific case studies on justice, the moral order, and gender relations. The influence of these richly diverse traditions is traced as well in the writings of African thinkers in the Diaspora.", "division": "Faculty of Arts and Science", "department": "New College", "prerequisites": "", "exclusions": "NEW252Y1, JAP256H1/JAP356H1", "level": 300, "campus": "UTSG", "term": "2018 Fall", "breadths": [2, 3], "meeting_sections": [{"code": "L0101", "instructors": ["A Ilmi"], "times": [{"day": "WEDNESDAY", "start": 36000, "end": 43200, "duration": 7200, "location": "WE 52"}], "size": 36, "enrolment": 0}]}