{"id": "NMC371H1S20191", "code": "NMC371H1S", "name": "Iran after Alexander", "description": "The history and culture of ancient Iran in the Seleucid and Parthian periods. Lectures and discussion will engage the complex question of Hellenism in the East and the levels of cultural, religious and political interactions between Greeks and Persians, as well as the formation of the Bactrian kingdom and of the Parthian empire.", "division": "Faculty of Arts and Science", "department": "Near & Middle Eastern Civilizations", "prerequisites": "", "exclusions": "", "level": 300, "campus": "UTSG", "term": "2019 Winter", "breadths": [1], "meeting_sections": [{"code": "L0101", "instructors": ["M Brosius"], "times": [{"day": "TUESDAY", "start": 50400, "end": 57600, "duration": 7200, "location": "ES 4000"}], "size": 30, "enrolment": 0}]}