{"id": "NML420Y1Y20189", "code": "NML420Y1Y", "name": "The Jerusalem Talmud: Jewish Western Aramaic", "description": "The Talmud of the Land of Israel, also called Talmud Yerushalmi or Palestinian Talmud, is written in a mixture of Jewish Western Aramaic and Mishnaic Hebrew. It is the principal document of the Land of Israel in Late Antiquity. The course examines the legal argumentation, terminology and language which differ from those of the Babylonian Talmud. (Offered in alternate years)", "division": "Faculty of Arts and Science", "department": "Near & Middle Eastern Civilizations", "prerequisites": "Permission of instructor", "exclusions": "", "level": 400, "campus": "UTSG", "term": "2018 Fall", "breadths": [1, 2], "meeting_sections": [{"code": "L0101", "instructors": ["T Meacham"], "times": [{"day": "WEDNESDAY", "start": 32400, "end": 43200, "duration": 10800, "location": ""}], "size": 10, "enrolment": 0}]}