{"id": "NML467H1F20189", "code": "NML467H1F", "name": "Persian Literature: The Epic Tradition", "description": "Explores iconic masterpieces of classical Persian heroic and romantic epic poetry, including the Persian national epic, Shahnameh, of Ferdowsi; the magisterial odes of Khaqani; and the Khamseh, or Quintet, of Nezami and its many literary responses. Emphasizes close reading and analysis of the texts and their historical and cultural backgrounds.", "division": "Faculty of Arts and Science", "department": "Near & Middle Eastern Civilizations", "prerequisites": "NML360Y1 or adequate knowledge of Persian", "exclusions": "NML460Y1", "level": 400, "campus": "UTSG", "term": "2018 Fall", "breadths": [1], "meeting_sections": [{"code": "L0101", "instructors": ["A Moshiri"], "times": [{"day": "WEDNESDAY", "start": 50400, "end": 61200, "duration": 10800, "location": "BF 200"}], "size": 20, "enrolment": 0}]}