{"id": "PHL273H1S20191", "code": "PHL273H1S", "name": "Environmental Ethics", "description": "A study of environmental issues raising questions of concern to moral and political philosophers, such as property rights, responsibility for future generations, and the interaction of human beings with the rest of nature. Typical issues: sustainable development, alternative energy, the preservation of wilderness areas, animal rights.", "division": "Faculty of Arts and Science", "department": "Philosophy", "prerequisites": "", "exclusions": "PHLB02H3, PHL273H5", "level": 200, "campus": "UTSG", "term": "2019 Winter", "breadths": [3], "meeting_sections": [{"code": "L0101", "instructors": ["J Thomson"], "times": [{"day": "MONDAY", "start": 43200, "end": 48600, "duration": 5400, "location": "MP 102"}, {"day": "WEDNESDAY", "start": 43200, "end": 48600, "duration": 5400, "location": "MP 102"}], "size": 196, "enrolment": 0}]}