{"id": "PHL370H1S20195S", "code": "PHL370H1S2", "name": "Issues in Philosophy of Law", "description": "Major issues in philosophy of law, such as legal positivism and its critics, law and liberalism, feminist critiques of law, punishment and responsibility.", "division": "Faculty of Arts and Science", "department": "Philosophy", "prerequisites": "PHL271H1, 7.5 courses (in any field) with at least 1.5 in philosophy", "exclusions": "PHL370H5", "level": 300, "campus": "UTSG", "term": "2019 Summer S", "breadths": [2], "meeting_sections": []}