{"id": "PHL356H1F20189", "code": "PHL356H1F", "name": "Philosophy of Physics", "description": "Introduction to philosophical issues which arise in modern physics, especially in Relativity and Quantum Mechanics. Topics include: the nature of spacetime, conventionality in geometry, determinism, and the relation between observation and existence.", "division": "Faculty of Arts and Science", "department": "Philosophy", "prerequisites": "One full course in MAT/PHY; two full courses are recommended.", "exclusions": "", "level": 300, "campus": "UTSG", "term": "2018 Fall", "breadths": [2], "meeting_sections": [{"code": "L0101", "instructors": ["M Miller"], "times": [{"day": "TUESDAY", "start": 36000, "end": 46800, "duration": 10800, "location": "TF 201"}], "size": 40, "enrolment": 0}]}