{"id": "PMU351Y1Y20189", "code": "PMU351Y1Y", "name": "Piano \u2013 Instrumental Master Class ", "description": "An exploration of the piano chamber literature, especially that for piano and one other instrument. Pianists prepare and perform with student instrumentalists. One hour.", "division": "Faculty of Music", "department": "Faculty of Music", "prerequisites": "PMU251Y1, 252Y1.", "exclusions": "Piano Performance majors only.", "level": 300, "campus": "UTSG", "term": "2018 Fall", "breadths": [], "meeting_sections": [{"code": "P0201", "instructors": ["J Parker E Degli Esposti Elisi L Wong"], "times": [{"day": "TUESDAY", "start": 50400, "end": 54000, "duration": 3600, "location": "EJ 252"}, {"day": "TUESDAY", "start": 50400, "end": 54000, "duration": 3600, "location": "EJ 253"}, {"day": "TUESDAY", "start": 50400, "end": 54000, "duration": 3600, "location": "EJ 215"}, {"day": "TUESDAY", "start": 50400, "end": 54000, "duration": 3600, "location": "EJ 224"}], "size": 15, "enrolment": 0}, {"code": "P0101", "instructors": ["L Wong J Parker E Degli Esposti Elisi"], "times": [{"day": "TUESDAY", "start": 46800, "end": 50400, "duration": 3600, "location": "EJ 252"}, {"day": "TUESDAY", "start": 46800, "end": 50400, "duration": 3600, "location": "EJ 253"}, {"day": "TUESDAY", "start": 46800, "end": 50400, "duration": 3600, "location": "EJ 215"}, {"day": "TUESDAY", "start": 46800, "end": 50400, "duration": 3600, "location": "EJ 224"}], "size": 15, "enrolment": 0}]}