{"id": "POL486H1S20191", "code": "POL486H1S", "name": "Topics in International Politics I", "description": "For advanced students of international relations. Various topics are taken up each year, the content of which depends on the instructor.", "division": "Faculty of Arts and Science", "department": "Political Science", "prerequisites": "POL208Y1/POL208Y5/(POLB80H3, POLB81H3)", "exclusions": "", "level": 400, "campus": "UTSG", "term": "2019 Winter", "breadths": [3], "meeting_sections": [{"code": "L0101", "instructors": ["L Gilady"], "times": [{"day": "WEDNESDAY", "start": 43200, "end": 50400, "duration": 7200, "location": "OI 3312"}], "size": 15, "enrolment": 0}]}