{"id": "PSY380H1F20189", "code": "PSY380H1F", "name": "Vision Science", "description": "Integrates psychology, neuroscience, and computer science approaches to the study of vision science. Topics include: spatial vision; perception of objects, function, and category; motion perception; visual attention, memory, and imagery; and consciousness. Demonstrations/in-class experiments supplement lectures and readings.", "division": "Faculty of Arts and Science", "department": "Psychology", "prerequisites": "PSY201H1 (or exclusion), PSY280H1", "exclusions": "PSYC51H3", "level": 300, "campus": "UTSG", "term": "2018 Fall", "breadths": [4], "meeting_sections": [{"code": "L0101", "instructors": ["D Bernhardt-Walther"], "times": [{"day": "MONDAY", "start": 36000, "end": 46800, "duration": 10800, "location": "WW 119"}], "size": 50, "enrolment": 0}]}