{"id": "PSYD33H3S20191", "code": "PSYD33H3S", "name": "Current Topics in Clinical Psychology", "description": "An intensive examination of selected issues and research problems in abnormal psychology. The specific content will vary from year to year.", "division": "University of Toronto Scarborough", "department": "Psychology (UTSC)", "prerequisites": "[PSYB07H3 or STAB22H3 or STAB23H3] and PSYB32H3 and [0.5 credit at the C-level in PSY courses]", "exclusions": "PSY440H", "level": 400, "campus": "UTSC", "term": "2019 Winter", "breadths": [4], "meeting_sections": [{"code": "L01", "instructors": ["Z Campbell"], "times": [{"day": "TUESDAY", "start": 32400, "end": 39600, "duration": 7200, "location": "HL 010"}], "size": 24, "enrolment": 0}, {"code": "L02", "instructors": ["A Daros"], "times": [{"day": "MONDAY", "start": 54000, "end": 61200, "duration": 7200, "location": "HL 008"}], "size": 24, "enrolment": 0}, {"code": "L04", "instructors": ["T Grieder"], "times": [{"day": "THURSDAY", "start": 36000, "end": 43200, "duration": 7200, "location": "BV 359"}], "size": 24, "enrolment": 0}, {"code": "L03", "instructors": ["Z Campbell"], "times": [{"day": "WEDNESDAY", "start": 32400, "end": 39600, "duration": 7200, "location": "HL 008"}], "size": 24, "enrolment": 0}]}