{"id": "RLG341H1F20189", "code": "RLG341H1F", "name": "Dreaming of Zion: Exile and Return in Jewish Thought", "description": "An inquiry into the theme of exile and return in Judaism, often called the leading idea of Jewish religious consciousness. Starting from Egyptian slavery and the Babylonian exile, and culminating in the ideas of modern Zionism, the course will examine a cross-section of Jewish thinkers--ancient, medieval, and modern.", "division": "Faculty of Arts and Science", "department": "Department for the Study of Religion", "prerequisites": "RLG100Y1/RLG202Y1/RLG280Y1/RLG342Y1; see note above for general Prerequisites", "exclusions": "", "level": 300, "campus": "UTSG", "term": "2018 Fall", "breadths": [2], "meeting_sections": [{"code": "L0101", "instructors": ["K Green"], "times": [{"day": "WEDNESDAY", "start": 50400, "end": 57600, "duration": 7200, "location": "GB 404"}], "size": 30, "enrolment": 0}]}