{"id": "SLA280H1S20191", "code": "SLA280H1S", "name": "Introduction to Russian Asia: From Central Asia to Siberia", "description": "Introduction to geography, languages, people, literature, and the history of Russian Asia. Includes readings in history, exile narratives, articles on the linguistic geography of the languages of Russia including Russian, Siberian languages such as Yakut and Tungus, Turkic languages of Central Asia, Korean and Chinese as minority languages, with a special focus on language contact and language politics.", "division": "Faculty of Arts and Science", "department": "Slavic Languages and Literatures", "prerequisites": "None", "exclusions": "", "level": 200, "campus": "UTSG", "term": "2019 Winter", "breadths": [1], "meeting_sections": [{"code": "L0101", "instructors": ["M Franz C Kramer"], "times": [{"day": "WEDNESDAY", "start": 43200, "end": 50400, "duration": 7200, "location": "CR 403"}], "size": 50, "enrolment": 0}]}