{"id": "SMC155H1S20191", "code": "SMC155H1S", "name": "SMC One: The McLuhan Seminar in Creativity and Technology", "description": "This seminar is an interdisciplinary exploration of the relationship between creativity and technology. Inspired by the innovative thinking of Marshall McLuhan, it explores how the humanities relate to other fields of thought and research in addressing the individual, social and cultural experiences and effects of technological innovation. This course includes a mandatory travel component opportunity to Silicon Valley, California, the costs of which, including transportation, room and board, are covered by the University of St. Michael's College.", "division": "Faculty of Arts and Science", "department": "St. Michael's College", "prerequisites": "Admission to SMC One", "exclusions": "Innis One, Munk One, New One, Trinity One, Vic One, UC One, Woodsworth One, SMC165H1, SMC188H1, SMC189H1", "level": 100, "campus": "UTSG", "term": "2019 Winter", "breadths": [], "meeting_sections": [{"code": "L0101", "instructors": ["P Granata"], "times": [{"day": "FRIDAY", "start": 36000, "end": 43200, "duration": 7200, "location": ""}], "size": 20, "enrolment": 0}]}