{"id": "TMU130H1F20189", "code": "TMU130H1F", "name": "Music Theory I", "description": "Diatonic harmony. Principles of voice leading and harmonic progression. Introduction to musical form.", "division": "Faculty of Music", "department": "Faculty of Music", "prerequisites": "", "exclusions": "TMU120H1.", "level": 100, "campus": "UTSG", "term": "2018 Fall", "breadths": [], "meeting_sections": [{"code": "L0101", "instructors": ["M Sallmen"], "times": [{"day": "MONDAY", "start": 39600, "end": 43200, "duration": 3600, "location": "EJ 330"}, {"day": "WEDNESDAY", "start": 39600, "end": 43200, "duration": 3600, "location": "EJ 330"}, {"day": "THURSDAY", "start": 32400, "end": 36000, "duration": 3600, "location": "EJ 216"}], "size": 135, "enrolment": 0}, {"code": "L0201", "instructors": ["M Sallmen"], "times": [{"day": "MONDAY", "start": 39600, "end": 43200, "duration": 3600, "location": "EJ 330"}, {"day": "WEDNESDAY", "start": 39600, "end": 43200, "duration": 3600, "location": "EJ 330"}, {"day": "THURSDAY", "start": 36000, "end": 43200, "duration": 7200, "location": "EJ 216"}], "size": 35, "enrolment": 0}, {"code": "L0301", "instructors": ["M Sallmen"], "times": [{"day": "MONDAY", "start": 43200, "end": 46800, "duration": 3600, "location": "EJ 330"}, {"day": "WEDNESDAY", "start": 43200, "end": 46800, "duration": 3600, "location": "EJ 330"}, {"day": "THURSDAY", "start": 32400, "end": 36000, "duration": 3600, "location": "EJ 224"}], "size": 30, "enrolment": 0}, {"code": "L0401", "instructors": ["M Sallmen"], "times": [{"day": "MONDAY", "start": 43200, "end": 46800, "duration": 3600, "location": "EJ 330"}, {"day": "WEDNESDAY", "start": 43200, "end": 46800, "duration": 3600, "location": "EJ 330"}, {"day": "THURSDAY", "start": 36000, "end": 43200, "duration": 7200, "location": "EJ 310"}], "size": 30, "enrolment": 0}, {"code": "L0501", "instructors": ["K Hutchinson"], "times": [{"day": "WEDNESDAY", "start": 50400, "end": 57600, "duration": 7200, "location": "EJ 216"}], "size": 13, "enrolment": 0}]}