{"id": "TRN204H1S20191", "code": "TRN204H1S", "name": "Introduction to Law and Legal Reasoning", "description": "This course introduces students to legal reasoning through progressively complex exercises. First, hypotheticals expose students to basic skills required for legal reasoning. Second, they analyze simplified versions of specially selected concrete cases. Third, the course analyses real cases discussed in first year courses in law school.", "division": "Faculty of Arts and Science", "department": "Trinity College", "prerequisites": "Active in ASMAJ1618", "exclusions": "", "level": 200, "campus": "UTSG", "term": "2019 Winter", "breadths": [3], "meeting_sections": [{"code": "L0101", "instructors": ["A Niblett M Shaffer"], "times": [{"day": "FRIDAY", "start": 36000, "end": 43200, "duration": 7200, "location": "GI ---"}], "size": 75, "enrolment": 0}, {"code": "T0101", "instructors": [], "times": [{"day": "FRIDAY", "start": 50400, "end": 54000, "duration": 3600, "location": "LA 214"}], "size": 25, "enrolment": 0}, {"code": "T0201", "instructors": [], "times": [{"day": "THURSDAY", "start": 50400, "end": 54000, "duration": 3600, "location": "LA 341"}], "size": 25, "enrolment": 0}, {"code": "T0301", "instructors": [], "times": [{"day": "FRIDAY", "start": 46800, "end": 50400, "duration": 3600, "location": "LA 214"}], "size": 25, "enrolment": 0}]}