{"id": "VIC347H1F20189", "code": "VIC347H1F", "name": "Studies in Renaissance Performance", "description": "Studies in the development of new forms in music, drama and dance in the Renaissance. The course will consist of seminars and lectures, and may incorporate live performances taking place in Toronto in addition to recordings.", "division": "Faculty of Arts and Science", "department": "Victoria College", "prerequisites": "", "exclusions": "VIC347Y1", "level": 300, "campus": "UTSG", "term": "2018 Fall", "breadths": [1], "meeting_sections": [{"code": "L0101", "instructors": ["S Ross"], "times": [{"day": "THURSDAY", "start": 50400, "end": 57600, "duration": 7200, "location": "NF 006"}], "size": 30, "enrolment": 0}]}