{"id": "WGS370H1S20191", "code": "WGS370H1S", "name": "Utopian Visions, Activist Realities", "description": "Drawing on diversely situated case-studies, this course focuses on the ideals that inform struggles for social justice, and the mechanisms activists have employed to produce the change. Foci include the gendered implications of movement participation, local and transnational coalition, alternative community formation, and encounters with the state and inter/supra/transnational organizations.", "division": "Faculty of Arts and Science", "department": "Women and Gender Studies Institute", "prerequisites": "", "exclusions": "", "level": 300, "campus": "UTSG", "term": "2019 Winter", "breadths": [3], "meeting_sections": [{"code": "L0101", "instructors": ["J Taylor"], "times": [{"day": "THURSDAY", "start": 36000, "end": 43200, "duration": 7200, "location": "WI 523"}], "size": 50, "enrolment": 0}]}