{"id": "WGS334H1S20195S", "code": "WGS334H1S2", "name": "Special Topic in Women and Gender Studies", "description": "An upper level seminar. Subjects of study vary from year to year. Topic for 2011-2012: Life Writing. A theoretical and literary study of the practice of life writing. Students will learn about narrative styles and their potential for a feminist imaginary. The course will include works of oral history, creative biography and autobiography, personal memoir and poetry.", "division": "Faculty of Arts and Science", "department": "Women and Gender Studies Institute", "prerequisites": "", "exclusions": "", "level": 300, "campus": "UTSG", "term": "2019 Summer S", "breadths": [1], "meeting_sections": []}